merlya/__init__.py
merlya/agent/__init__.py
merlya/agent/agent_factory.py
merlya/agent/confirmation.py
merlya/agent/history.py
merlya/agent/main.py
merlya/agent/prompts.py
merlya/agent/tools_common.py
merlya/agent/tools_files.py
merlya/agent/tools_mcp.py
merlya/agent/tools_security.py
merlya/agent/tools_system.py
merlya/agent/tools_web.py
merlya/agent/tracker.py
merlya/agent/types.py
merlya/agent/orchestrator/__init__.py
merlya/agent/orchestrator/center_integration.py
merlya/agent/orchestrator/center_tools.py
merlya/agent/orchestrator/completion.py
merlya/agent/orchestrator/constants.py
merlya/agent/orchestrator/core.py
merlya/agent/orchestrator/delegation_tools.py
merlya/agent/orchestrator/mcp_tools.py
merlya/agent/orchestrator/models.py
merlya/agent/orchestrator/prompts.py
merlya/agent/orchestrator/sanitization.py
merlya/agent/orchestrator/specialist_runner.py
merlya/agent/orchestrator/specialist_tools.py
merlya/agent/orchestrator/target_normalization.py
merlya/agent/orchestrator/utility_tools.py
merlya/agent/specialists/__init__.py
merlya/agent/specialists/deps.py
merlya/agent/specialists/diagnostic.py
merlya/agent/specialists/elevation.py
merlya/agent/specialists/execution.py
merlya/agent/specialists/prompts.py
merlya/agent/specialists/query.py
merlya/agent/specialists/security.py
merlya/agent/specialists/types.py
merlya/agent/tools/__init__.py
merlya/agent/tools/core/__init__.py
merlya/agent/tools/core/bash.py
merlya/agent/tools/core/credentials.py
merlya/agent/tools/core/hosts.py
merlya/agent/tools/core/ssh.py
merlya/agent/tools/core/user_interaction.py
merlya/audit/__init__.py
merlya/audit/formatters.py
merlya/audit/log_methods.py
merlya/audit/logger.py
merlya/audit/models.py
merlya/audit/storage.py
merlya/capabilities/__init__.py
merlya/capabilities/cache.py
merlya/capabilities/detector.py
merlya/capabilities/models.py
merlya/centers/__init__.py
merlya/centers/base.py
merlya/centers/change.py
merlya/centers/diagnostic.py
merlya/centers/registry.py
merlya-0.8.2.dist-info/METADATA
merlya-0.8.2.dist-info/WHEEL
merlya-0.8.2.dist-info/entry_points.txt
merlya-0.8.2.dist-info/licenses/LICENSE
merlya-0.8.2.dist-info/RECORD
