Metadata-Version: 2.4
Name: merlya
Version: 0.8.2
Summary: Merlya - AI-powered infrastructure assistant
Author-email: Cedric <infra@merlya.fr>
License: MIT
License-File: LICENSE
Keywords: ai,automation,devops,infrastructure,ssh
Classifier: Development Status :: 3 - Alpha
Classifier: Environment :: Console
Classifier: Intended Audience :: Developers
Classifier: Intended Audience :: System Administrators
Classifier: License :: OSI Approved :: MIT License
Classifier: Operating System :: OS Independent
Classifier: Programming Language :: Python :: 3.11
Classifier: Programming Language :: Python :: 3.12
Classifier: Programming Language :: Python :: 3.13
Classifier: Topic :: System :: Systems Administration
Requires-Python: >=3.11
Requires-Dist: aiosqlite>=0.21
Requires-Dist: anthropic>=0.75
Requires-Dist: asyncssh>=2.21
Requires-Dist: ddgs>=9.9
Requires-Dist: httpx>=0.28
Requires-Dist: jinja2>=3.1
Requires-Dist: keyring>=25.5
Requires-Dist: keyrings-alt>=5.0; sys_platform == 'linux'
Requires-Dist: logfire[system-metrics]>=4.0
Requires-Dist: loguru>=0.7
Requires-Dist: mcp>=1.23.0
Requires-Dist: numpy>=1.26
Requires-Dist: openai>=1.50
Requires-Dist: packaging>=24.0
Requires-Dist: prompt-toolkit>=3.0
Requires-Dist: psutil>=6.1
Requires-Dist: pydantic-ai>=1.26
Requires-Dist: pydantic>=2.10
Requires-Dist: pyyaml>=6.0
Requires-Dist: rich>=14.0
Requires-Dist: secretstorage>=3.3; sys_platform == 'linux'
Requires-Dist: urllib3>=2.6.0
Provides-Extra: dev
Requires-Dist: mypy>=1.13; extra == 'dev'
Requires-Dist: pytest-asyncio>=0.24; extra == 'dev'
Requires-Dist: pytest-cov>=6.0; extra == 'dev'
Requires-Dist: pytest>=8.3; extra == 'dev'
Requires-Dist: ruff>=0.8; extra == 'dev'
Requires-Dist: types-pyyaml>=6.0; extra == 'dev'
Provides-Extra: docs
Requires-Dist: mkdocs-material>=9.5.0; extra == 'docs'
Requires-Dist: mkdocs-minify-plugin>=0.8.0; extra == 'docs'
Requires-Dist: mkdocs-static-i18n>=1.2.0; extra == 'docs'
Requires-Dist: mkdocs>=1.6.0; extra == 'docs'
Requires-Dist: pymdown-extensions>=10.0; extra == 'docs'
